gunshotmatch_cli/__init__.py
gunshotmatch_cli/__main__.py
gunshotmatch_cli/decision_tree.py
gunshotmatch_cli/py.typed
gunshotmatch_cli-0.9.0.dist-info/LICENSE
gunshotmatch_cli-0.9.0.dist-info/METADATA
gunshotmatch_cli-0.9.0.dist-info/WHEEL
gunshotmatch_cli-0.9.0.dist-info/entry_points.txt
gunshotmatch_cli-0.9.0.dist-info/RECORD
