Metadata-Version: 2.2
Name: gunshotmatch-cli
Version: 0.9.0
Summary: GunShotMatch Command-Line Interface.
Author-email: Dominic Davis-Foster <dominic@davis-foster.co.uk>
License: MIT
Home-page: https://github.com/GunShotMatch/gunshotmatch-cli
Project-URL: Issue Tracker, https://github.com/GunShotMatch/gunshotmatch-cli/issues
Project-URL: Source Code, https://github.com/GunShotMatch/gunshotmatch-cli
Platform: Windows
Platform: macOS
Platform: Linux
Classifier: License :: OSI Approved :: MIT License
Classifier: Operating System :: OS Independent
Classifier: Programming Language :: Python
Classifier: Programming Language :: Python :: 3 :: Only
Classifier: Programming Language :: Python :: 3.8
Classifier: Programming Language :: Python :: 3.9
Classifier: Programming Language :: Python :: 3.10
Classifier: Programming Language :: Python :: 3.11
Classifier: Programming Language :: Python :: 3.12
Classifier: Programming Language :: Python :: Implementation :: CPython
Classifier: Typing :: Typed
Requires-Python: >=3.8
Requires-Dist: click>=8.1.7
Requires-Dist: consolekit>=1.5.2
Requires-Dist: domdf-python-tools>=3.6.1
Requires-Dist: gunshotmatch-pipeline>=0.8.1
Requires-Dist: gunshotmatch-reports>=0.1.0
Requires-Dist: libgunshotmatch>=0.12.0
Requires-Dist: libgunshotmatch-mpl>=0.1.0.post1
Requires-Dist: numpy>=1.22
Requires-Dist: scikit-learn>=1.3.2
Requires-Dist: sdjson>=0.4.0
